<?xml version="1.0" encoding="UTF-8"?>
<schemalist gettext-domain="gsettings-hawaii-schemas">
  <schema path="/org/maui/desktop/interface/" id="org.maui.desktop.interface">
    <key type="b" name="enable-animations">
      <default>true</default>
      <summary>Enable Animations</summary>
      <description>Whether animations should be displayed. Note: This is a global key, it changes the behaviour of the window manager, the panel etc.</description>
    </key>
    <key type="s" name="font-name">
      <default>'DejaVu Sans'</default>
      <summary>Font</summary>
      <description>Font used to display user interface elements, such as check box labels, menu items, etc.</description>
    </key>
    <key type="i" name="font-size">
      <default>11</default>
      <summary>Font Size</summary>
      <description>Point size of the font used to display user interface elements, such as check box labels, menu items, etc.</description>
    </key>
    <key type="s" name="monospace-font-name">
      <default>'DejaVu Sans Mono'</default>
      <summary>Fixed-width Font</summary>
      <description>Font used to display fixed-width characters, mostly used by terminal windows.</description>
    </key>
    <key type="i" name="monospace-font-size">
      <default>11</default>
      <summary>Fixed-width Font Size</summary>
      <description>Point size of the font used to display fixed-width characters, mostly used by terminal windows.</description>
    </key>
    <key type="s" name="decorator">
      <default>'Vanish'</default>
      <summary>Window Decorator Style</summary>
      <description>Style used to draw window decorations.</description>
    </key>
    <key type="s" name="style">
      <default>'Vanish'</default>
      <summary>User Interface Style</summary>
      <description>Style used to draw all user interface elements.</description>
    </key>
    <key type="s" name="color-scheme">
      <default>'Default'</default>
      <summary>User Interface Color Scheme</summary>
      <description>Color scheme to be applied to the user interface style. If empty, the default style's palette is used.</description>
    </key>
    <key type="s" name="icon-theme">
      <default>'Vanish'</default>
      <summary>Icon Theme</summary>
      <description>Theme used for all the icons.</description>
    </key>
    <key type="i" name="small-icon-size">
      <default>22</default>
      <summary>Small Icon Size</summary>
      <description>Size of the small icons.</description>
    </key>
    <key type="i" name="large-icon-size">
      <default>48</default>
      <summary>Large Icon Size</summary>
      <description>Size of the large icons.</description>
    </key>
    <key type="i" name="toolbar-icon-size">
      <default>24</default>
      <summary>Toolbar Icon Size</summary>
      <description>Size of toolbar icons.</description>
    </key>
    <key type="i" name="iconview-icon-size">
      <default>48</default>
      <summary>Icon View Icon Size</summary>
      <description>Size of icon view icons.</description>
    </key>
    <key type="s" name="cursor-theme">
      <default>'Vanish'</default>
      <summary>Cursor Theme</summary>
      <description>Cursor theme name.</description>
    </key>
    <key type="i" name="cursor-size">
      <default>24</default>
      <summary>Cursor Size</summary>
      <description>Size of the cursor used as cursor theme.</description>
    </key>
    <key name="toolbutton-style" enum="org.maui.desktop.ToolButtonStyle">
      <default>'icon-only'</default>
      <summary>Toolbar Buttons Style</summary>
      <description>Style of toolbar buttons. Valid values are "icon-only", "text-only", "text-beside-icon" or "text-under-icon".</description>
    </key>
  </schema>
</schemalist>
